django_chunk_upload/__init__.py
django_chunk_upload/admin.py
django_chunk_upload/constants.py
django_chunk_upload/exceptions.py
django_chunk_upload/models.py
django_chunk_upload/response.py
django_chunk_upload/settings.py
django_chunk_upload/tests.py
django_chunk_upload/views.py
django_chunk_upload-2.0.0.dist-info/LICENSE.txt
django_chunk_upload-2.0.0.dist-info/METADATA
django_chunk_upload-2.0.0.dist-info/WHEEL
django_chunk_upload-2.0.0.dist-info/top_level.txt
django_chunk_upload-2.0.0.dist-info/RECORD
