Metadata-Version: 2.1
Name: django-chunk-upload
Version: 2.0.0
Summary: Upload large files to Django in multiple chunks, with the ability to resume if the upload is interrupted.
Home-page: https://github.com/jerinpetergeorge/django-chunk-upload
Author: Jerin Peter George
Author-email: jerinpetergeorge@gmail.com
License: MIT-Zero
Download-URL: https://github.com/jerinpetergeorge/django-chunk-upload/tarball/2.0.0
Platform: UNKNOWN
